flet_iconoir/__init__.py
flet_iconoir/iconoir_icon.py
flet_iconoir/iconoir_icon_button.py
flet_iconoir/icons/__init__.py
flet_iconoir/icons/LICENSE
flet_iconoir/icons/regular/__init__.py
flet_iconoir/icons/regular/accessibility-sign.svg
flet_iconoir/icons/regular/accessibility-tech.svg
flet_iconoir/icons/regular/accessibility.svg
flet_iconoir/icons/regular/activity.svg
flet_iconoir/icons/regular/adobe-after-effects.svg
flet_iconoir/icons/regular/adobe-illustrator.svg
flet_iconoir/icons/regular/adobe-indesign.svg
flet_iconoir/icons/regular/adobe-lightroom.svg
flet_iconoir/icons/regular/adobe-photoshop.svg
flet_iconoir/icons/regular/adobe-xd.svg
flet_iconoir/icons/regular/african-tree.svg
flet_iconoir/icons/regular/agile.svg
flet_iconoir/icons/regular/air-conditioner.svg
flet_iconoir/icons/regular/airplane-helix-45deg.svg
flet_iconoir/icons/regular/airplane-helix.svg
flet_iconoir/icons/regular/airplane-off.svg
flet_iconoir/icons/regular/airplane-rotation.svg
flet_iconoir/icons/regular/airplane.svg
flet_iconoir/icons/regular/airplay.svg
flet_iconoir/icons/regular/alarm.svg
flet_iconoir/icons/regular/album-carousel.svg
flet_iconoir/icons/regular/album-list.svg
flet_iconoir/icons/regular/album-open.svg
flet_iconoir/icons/regular/album.svg
flet_iconoir/icons/regular/align-bottom-box.svg
flet_iconoir/icons/regular/align-center.svg
flet_iconoir/icons/regular/align-horizontal-centers.svg
flet_iconoir/icons/regular/align-horizontal-spacing.svg
flet_iconoir/icons/regular/align-justify.svg
flet_iconoir/icons/regular/align-left-box.svg
flet_iconoir/icons/regular/align-left.svg
flet_iconoir/icons/regular/align-right-box.svg
flet_iconoir/icons/regular/align-right.svg
flet_iconoir/icons/regular/align-top-box.svg
flet_iconoir/icons/regular/align-vertical-centers.svg
flet_iconoir/icons/regular/align-vertical-spacing.svg
flet_iconoir/icons/regular/angle-tool.svg
flet_iconoir/icons/regular/antenna-off.svg
flet_iconoir/icons/regular/antenna-signal-tag.svg
flet_iconoir-0.3.0.dist-info/METADATA
flet_iconoir-0.3.0.dist-info/WHEEL
flet_iconoir-0.3.0.dist-info/RECORD
