Metadata-Version: 2.1
Name: flet-iconoir
Version: 0.3.0
Summary: the Iconoir library, wrapped for Flet.
License: MIT
Author: hex benjamin
Author-email: hex@hexbenjam.in
Requires-Python: >=3.11,<3.13
Classifier: License :: OSI Approved :: MIT License
Classifier: Programming Language :: Python :: 3
Classifier: Programming Language :: Python :: 3.11
Classifier: Programming Language :: Python :: 3.12
Requires-Dist: flet (>=0.22.0,<0.23.0)
